{
  "version": "0.0.1",
  "records": [
    {
      "id": "d_main_10_03_s_1",
      "group_id": "d_main_10_03_s",
      "speech_window": "Speech",
      "highlight": "anis",
      "speaker": "anis",
      "scenario_localkey": "d_main_10_03_s_1",
      "play_lipSync": true,
      "characters": [
        {
          "show_char_id": "anis",
          "set_char_position": "1",
          "set_char_anim": "idle"
        },
        {
          "show_char_id": "vesti",
          "set_char_position": "13",
          "set_char_anim": "shy"
        },
        {
          "show_char_id": "emma",
          "set_char_position": "15",
          "set_char_anim": "worry"
        },
        {},
        {},
        {},
        {},
        {},
        {},
        {}
      ],
      "set_background": "Desert_01",
      "set_start_camera": "12",
      "set_end_camera": "12",
      "set_camera_duration": 1.0,
      "play_bgm": "bgm_areah_a",
      "effects": [
        {},
        {}
      ]
    },
    {
      "id": "d_main_10_03_s_2",
      "group_id": "d_main_10_03_s",
      "speech_window": "Speech",
      "highlight": "anis",
      "speaker": "anis",
      "scenario_localkey": "d_main_10_03_s_2",
      "play_lipSync": true,
      "characters": [
        {
          "set_char_position": "1",
          "set_char_anim": "idle"
        },
        {
          "set_char_position": "13",
          "set_char_anim": "shy"
        },
        {
          "set_char_position": "15",
          "set_char_anim": "worry"
        },
        {},
        {},
        {},
        {},
        {},
        {},
        {}
      ],
      "set_start_camera": "12",
      "set_end_camera": "12",
      "set_camera_duration": 1.0,
      "effects": [
        {},
        {}
      ]
    },
    {
      "id": "d_main_10_03_s_3",
      "group_id": "d_main_10_03_s",
      "speech_window": "Speech",
      "highlight": "vesti",
      "speaker": "vesti",
      "scenario_localkey": "d_main_10_03_s_3",
      "play_lipSync": false,
      "characters": [
        {
          "set_char_position": "1",
          "set_char_anim": "idle"
        },
        {
          "set_char_position": "13",
          "set_char_anim": "shy"
        },
        {
          "set_char_position": "15",
          "set_char_anim": "worry"
        },
        {},
        {},
        {},
        {},
        {},
        {},
        {}
      ],
      "set_start_camera": "12",
      "set_end_camera": "12",
      "set_camera_duration": 1.0,
      "effects": [
        {},
        {}
      ]
    },
    {
      "id": "d_main_10_03_s_4",
      "group_id": "d_main_10_03_s",
      "speech_window": "Speech",
      "highlight": "anis",
      "speaker": "anis",
      "scenario_localkey": "d_main_10_03_s_4",
      "play_lipSync": true,
      "characters": [
        {
          "set_char_position": "1",
          "set_char_anim": "worry"
        },
        {
          "set_char_position": "13",
          "set_char_anim": "shy"
        },
        {
          "set_char_position": "15",
          "set_char_anim": "worry"
        },
        {},
        {},
        {},
        {},
        {},
        {},
        {}
      ],
      "set_start_camera": "12",
      "set_end_camera": "12",
      "set_camera_duration": 1.0,
      "effects": [
        {},
        {}
      ]
    },
    {
      "id": "d_main_10_03_s_5",
      "group_id": "d_main_10_03_s",
      "speech_window": "Speech",
      "highlight": "anis",
      "speaker": "anis",
      "scenario_localkey": "d_main_10_03_s_5",
      "play_lipSync": true,
      "characters": [
        {
          "set_char_position": "1",
          "set_char_anim": "worry"
        },
        {
          "set_char_position": "13",
          "set_char_anim": "shy"
        },
        {
          "set_char_position": "15",
          "set_char_anim": "worry"
        },
        {},
        {},
        {},
        {},
        {},
        {},
        {}
      ],
      "set_start_camera": "12",
      "set_end_camera": "12",
      "set_camera_duration": 1.0,
      "effects": [
        {},
        {}
      ]
    },
    {
      "id": "d_main_10_03_s_6",
      "group_id": "d_main_10_03_s",
      "speech_window": "Speech",
      "highlight": "vesti",
      "speaker": "vesti",
      "scenario_localkey": "d_main_10_03_s_6",
      "play_lipSync": true,
      "characters": [
        {
          "set_char_position": "1",
          "set_char_anim": "worry"
        },
        {
          "set_char_position": "13",
          "set_char_anim": "idle"
        },
        {
          "set_char_position": "15",
          "set_char_anim": "worry"
        },
        {},
        {},
        {},
        {},
        {},
        {},
        {}
      ],
      "set_start_camera": "12",
      "set_end_camera": "12",
      "set_camera_duration": 1.0,
      "effects": [
        {},
        {}
      ]
    },
    {
      "id": "d_main_10_03_s_7",
      "group_id": "d_main_10_03_s",
      "speech_window": "Speech",
      "highlight": "anis",
      "speaker": "anis",
      "scenario_localkey": "d_main_10_03_s_7",
      "play_lipSync": true,
      "characters": [
        {
          "set_char_position": "1",
          "set_char_anim": "worry"
        },
        {
          "set_char_position": "13",
          "set_char_anim": "idle"
        },
        {
          "set_char_position": "15",
          "set_char_anim": "worry"
        },
        {},
        {},
        {},
        {},
        {},
        {},
        {}
      ],
      "set_start_camera": "12",
      "set_end_camera": "12",
      "set_camera_duration": 1.0,
      "effects": [
        {},
        {}
      ]
    },
    {
      "id": "d_main_10_03_s_8",
      "group_id": "d_main_10_03_s",
      "speech_window": "Speech",
      "highlight": "vesti",
      "speaker": "vesti",
      "scenario_localkey": "d_main_10_03_s_8",
      "play_lipSync": true,
      "characters": [
        {
          "set_char_position": "1",
          "set_char_anim": "worry"
        },
        {
          "set_char_position": "13",
          "set_char_anim": "delight"
        },
        {
          "set_char_position": "15",
          "set_char_anim": "worry"
        },
        {},
        {},
        {},
        {},
        {},
        {},
        {}
      ],
      "set_start_camera": "12",
      "set_end_camera": "12",
      "set_camera_duration": 1.0,
      "effects": [
        {},
        {}
      ]
    },
    {
      "id": "d_main_10_03_s_9",
      "group_id": "d_main_10_03_s",
      "speech_window": "Speech",
      "highlight": "vesti",
      "speaker": "vesti",
      "scenario_localkey": "d_main_10_03_s_9",
      "play_lipSync": true,
      "characters": [
        {
          "set_char_position": "1",
          "set_char_anim": "worry"
        },
        {
          "set_char_position": "13",
          "set_char_anim": "delight"
        },
        {
          "set_char_position": "15",
          "set_char_anim": "worry"
        },
        {},
        {},
        {},
        {},
        {},
        {},
        {}
      ],
      "set_start_camera": "12",
      "set_end_camera": "12",
      "set_camera_duration": 1.0,
      "effects": [
        {},
        {}
      ]
    },
    {
      "id": "d_main_10_03_s_10",
      "group_id": "d_main_10_03_s",
      "speech_window": "Speech",
      "highlight": "anis",
      "speaker": "anis",
      "scenario_localkey": "d_main_10_03_s_10",
      "play_lipSync": false,
      "characters": [
        {
          "set_char_position": "1",
          "set_char_anim": "void"
        },
        {
          "set_char_position": "13",
          "set_char_anim": "delight"
        },
        {
          "set_char_position": "15",
          "set_char_anim": "worry"
        },
        {},
        {},
        {},
        {},
        {},
        {},
        {}
      ],
      "set_start_camera": "12",
      "set_end_camera": "12",
      "set_camera_duration": 1.0,
      "effects": [
        {},
        {}
      ]
    },
    {
      "id": "d_main_10_03_s_11",
      "group_id": "d_main_10_03_s",
      "speech_window": "Speech",
      "highlight": "vesti",
      "speaker": "vesti",
      "scenario_localkey": "d_main_10_03_s_11",
      "play_lipSync": true,
      "characters": [
        {
          "set_char_position": "1",
          "set_char_anim": "void"
        },
        {
          "set_char_position": "13",
          "set_char_anim": "idle"
        },
        {
          "set_char_position": "15",
          "set_char_anim": "worry"
        },
        {},
        {},
        {},
        {},
        {},
        {},
        {}
      ],
      "set_start_camera": "12",
      "set_end_camera": "12",
      "set_camera_duration": 1.0,
      "effects": [
        {},
        {}
      ]
    },
    {
      "id": "d_main_10_03_s_12",
      "group_id": "d_main_10_03_s",
      "speech_window": "Speech",
      "highlight": "anis",
      "speaker": "anis",
      "scenario_localkey": "d_main_10_03_s_12",
      "play_lipSync": true,
      "characters": [
        {
          "set_char_position": "1",
          "set_char_anim": "idle"
        },
        {
          "set_char_position": "13",
          "set_char_anim": "idle"
        },
        {
          "set_char_position": "15",
          "set_char_anim": "worry"
        },
        {},
        {},
        {},
        {},
        {},
        {},
        {}
      ],
      "set_start_camera": "12",
      "set_end_camera": "12",
      "set_camera_duration": 1.0,
      "effects": [
        {},
        {}
      ]
    },
    {
      "id": "d_main_10_03_s_13",
      "group_id": "d_main_10_03_s",
      "speech_window": "Speech",
      "highlight": "anis",
      "speaker": "anis",
      "scenario_localkey": "d_main_10_03_s_13",
      "play_lipSync": true,
      "characters": [
        {
          "set_char_position": "1",
          "set_char_anim": "idle"
        },
        {
          "set_char_position": "13",
          "set_char_anim": "idle"
        },
        {
          "set_char_position": "15",
          "set_char_anim": "worry"
        },
        {},
        {},
        {},
        {},
        {},
        {},
        {}
      ],
      "set_start_camera": "12",
      "set_end_camera": "12",
      "set_camera_duration": 1.0,
      "effects": [
        {},
        {}
      ]
    },
    {
      "id": "d_main_10_03_s_14",
      "group_id": "d_main_10_03_s",
      "speech_window": "Speech",
      "highlight": "shifty",
      "speaker": "shifty",
      "scenario_localkey": "d_main_10_03_s_14",
      "play_lipSync": true,
      "characters": [
        {
          "set_char_position": "1",
          "set_char_anim": "void"
        },
        {
          "set_char_position": "13",
          "set_char_anim": "idle"
        },
        {
          "set_char_position": "15",
          "set_char_anim": "worry"
        },
        {
          "show_char_id": "shifty",
          "set_char_position": "OP_leftup",
          "set_char_anim": "idle"
        },
        {},
        {},
        {},
        {},
        {},
        {}
      ],
      "set_start_camera": "12",
      "set_end_camera": "12",
      "set_camera_duration": 1.0,
      "effects": [
        {},
        {}
      ]
    },
    {
      "id": "d_main_10_03_s_15",
      "group_id": "d_main_10_03_s",
      "speech_window": "Speech",
      "highlight": "shifty",
      "speaker": "shifty",
      "scenario_localkey": "d_main_10_03_s_15",
      "play_lipSync": true,
      "characters": [
        {
          "set_char_position": "1",
          "set_char_anim": "void"
        },
        {
          "set_char_position": "13",
          "set_char_anim": "idle"
        },
        {
          "set_char_position": "15",
          "set_char_anim": "worry"
        },
        {
          "set_char_position": "OP_leftup",
          "set_char_anim": "idle"
        },
        {},
        {},
        {},
        {},
        {},
        {}
      ],
      "set_start_camera": "12",
      "set_end_camera": "12",
      "set_camera_duration": 1.0,
      "effects": [
        {},
        {}
      ]
    },
    {
      "id": "d_main_10_03_s_16",
      "group_id": "d_main_10_03_s",
      "speech_window": "Speech",
      "highlight": "emma",
      "speaker": "emma",
      "scenario_localkey": "d_main_10_03_s_16",
      "play_lipSync": true,
      "characters": [
        {
          "set_char_position": "1",
          "set_char_anim": "void"
        },
        {
          "set_char_position": "13",
          "set_char_anim": "idle"
        },
        {
          "set_char_position": "15",
          "set_char_anim": "worry"
        },
        {
          "hide_char_id": "shifty",
          "set_char_position": "OP_leftup",
          "set_char_anim": "idle"
        },
        {},
        {},
        {},
        {},
        {},
        {}
      ],
      "set_start_camera": "15",
      "set_end_camera": "15",
      "set_camera_duration": 1.0,
      "effects": [
        {},
        {}
      ]
    },
    {
      "id": "d_main_10_03_s_17",
      "group_id": "d_main_10_03_s",
      "speech_window": "Speech",
      "highlight": "vesti",
      "speaker": "vesti",
      "scenario_localkey": "d_main_10_03_s_17",
      "play_lipSync": true,
      "characters": [
        {
          "set_char_position": "1",
          "set_char_anim": "void"
        },
        {
          "set_char_position": "13",
          "set_char_anim": "idle"
        },
        {
          "set_char_position": "15",
          "set_char_anim": "worry"
        },
        {},
        {},
        {},
        {},
        {},
        {},
        {}
      ],
      "set_start_camera": "15",
      "set_end_camera": "12",
      "set_camera_duration": 1.0,
      "effects": [
        {},
        {}
      ]
    },
    {
      "id": "d_main_10_03_s_18",
      "group_id": "d_main_10_03_s",
      "speech_window": "Speech",
      "highlight": "anis",
      "speaker": "anis",
      "scenario_localkey": "d_main_10_03_s_18",
      "play_lipSync": true,
      "characters": [
        {
          "set_char_position": "1",
          "set_char_anim": "void"
        },
        {
          "set_char_position": "13",
          "set_char_anim": "idle"
        },
        {
          "set_char_position": "15",
          "set_char_anim": "worry"
        },
        {},
        {},
        {},
        {},
        {},
        {},
        {}
      ],
      "set_start_camera": "12",
      "set_end_camera": "12",
      "set_camera_duration": 1.0,
      "effects": [
        {},
        {}
      ]
    },
    {
      "id": "d_main_10_03_s_19",
      "group_id": "d_main_10_03_s",
      "speech_window": "Speech",
      "highlight": "vesti",
      "speaker": "vesti",
      "scenario_localkey": "d_main_10_03_s_19",
      "play_lipSync": true,
      "characters": [
        {
          "set_char_position": "1",
          "set_char_anim": "void"
        },
        {
          "set_char_position": "13",
          "set_char_anim": "idle"
        },
        {
          "set_char_position": "15",
          "set_char_anim": "worry"
        },
        {},
        {},
        {},
        {},
        {},
        {},
        {}
      ],
      "set_start_camera": "12",
      "set_end_camera": "XS_130",
      "set_camera_duration": 1.0,
      "effects": [
        {},
        {}
      ]
    },
    {
      "id": "d_main_10_03_s_20",
      "group_id": "d_main_10_03_s",
      "speech_window": "Speech",
      "highlight": "vesti",
      "speaker": "vesti",
      "scenario_localkey": "d_main_10_03_s_20",
      "play_lipSync": true,
      "characters": [
        {
          "set_char_position": "1",
          "set_char_anim": "void"
        },
        {
          "set_char_position": "13",
          "set_char_anim": "idle"
        },
        {
          "set_char_position": "15",
          "set_char_anim": "worry"
        },
        {},
        {},
        {},
        {},
        {},
        {},
        {}
      ],
      "set_start_camera": "XS_130",
      "set_end_camera": "XS_130",
      "set_camera_duration": 1.0,
      "effects": [
        {},
        {}
      ]
    },
    {
      "id": "d_main_10_03_s_21",
      "group_id": "d_main_10_03_s",
      "speech_window": "Speech",
      "highlight": "vesti",
      "speaker": "vesti",
      "scenario_localkey": "d_main_10_03_s_21",
      "play_lipSync": true,
      "characters": [
        {
          "set_char_position": "1",
          "set_char_anim": "void"
        },
        {
          "set_char_position": "13",
          "set_char_anim": "angry"
        },
        {
          "set_char_position": "15",
          "set_char_anim": "worry"
        },
        {},
        {},
        {},
        {},
        {},
        {},
        {}
      ],
      "set_start_camera": "XS_130",
      "set_end_camera": "XS_1300",
      "set_camera_duration": 1.0,
      "effects": [
        {},
        {}
      ]
    },
    {
      "id": "d_main_10_03_s_22",
      "group_id": "d_main_10_03_s",
      "speech_window": "Narration",
      "speaker": "Narration",
      "scenario_localkey": "d_main_10_03_s_22",
      "play_lipSync": false,
      "characters": [
        {
          "set_char_position": "1",
          "set_char_anim": "void"
        },
        {
          "set_char_position": "5",
          "set_char_anim": "angry"
        },
        {
          "set_char_position": "15",
          "set_char_anim": "worry"
        },
        {},
        {},
        {},
        {},
        {},
        {},
        {}
      ],
      "set_start_camera": "XS_1300",
      "set_end_camera": "13",
      "set_camera_duration": 1.0,
      "effects": [
        {},
        {}
      ]
    },
    {
      "id": "d_main_10_03_s_23",
      "group_id": "d_main_10_03_s",
      "speech_window": "Speech",
      "highlight": "anis",
      "speaker": "anis",
      "scenario_localkey": "d_main_10_03_s_23",
      "play_lipSync": true,
      "characters": [
        {
          "set_char_position": "1",
          "set_char_anim": "angry"
        },
        {
          "hide_char_id": "vesti",
          "set_char_position": "5",
          "set_char_anim": "angry"
        },
        {
          "set_char_position": "15",
          "set_char_anim": "worry"
        },
        {},
        {},
        {},
        {},
        {},
        {},
        {}
      ],
      "set_start_camera": "13",
      "set_end_camera": "1",
      "set_camera_duration": 1.0,
      "effects": [
        {},
        {}
      ]
    },
    {
      "id": "d_main_10_03_s_24",
      "group_id": "d_main_10_03_s",
      "speech_window": "Speech",
      "highlight": "emma",
      "speaker": "emma",
      "scenario_localkey": "d_main_10_03_s_24",
      "play_lipSync": true,
      "characters": [
        {
          "set_char_position": "1",
          "set_char_anim": "angry"
        },
        {},
        {
          "set_char_position": "13",
          "set_char_anim": "delight"
        },
        {},
        {},
        {},
        {},
        {},
        {},
        {}
      ],
      "set_start_camera": "1",
      "set_end_camera": "12",
      "set_camera_duration": 1.0,
      "effects": [
        {},
        {}
      ]
    },
    {
      "id": "d_main_10_03_s_25",
      "group_id": "d_main_10_03_s",
      "speech_window": "Speech",
      "highlight": "anis",
      "speaker": "anis",
      "scenario_localkey": "d_main_10_03_s_25",
      "play_lipSync": true,
      "characters": [
        {
          "set_char_position": "1",
          "set_char_anim": "angry"
        },
        {},
        {
          "set_char_position": "13",
          "set_char_anim": "delight"
        },
        {},
        {},
        {},
        {},
        {},
        {},
        {}
      ],
      "set_start_camera": "12",
      "set_end_camera": "12",
      "set_camera_duration": 1.0,
      "effects": [
        {},
        {}
      ]
    },
    {
      "id": "d_main_10_03_s_26",
      "group_id": "d_main_10_03_s",
      "speech_window": "Speech",
      "highlight": "emma",
      "speaker": "emma",
      "scenario_localkey": "d_main_10_03_s_26",
      "play_lipSync": true,
      "characters": [
        {
          "set_char_position": "1",
          "set_char_anim": "angry"
        },
        {},
        {
          "set_char_position": "13",
          "set_char_anim": "idle"
        },
        {},
        {},
        {},
        {},
        {},
        {},
        {}
      ],
      "set_start_camera": "12",
      "set_end_camera": "130",
      "set_camera_duration": 1.0,
      "effects": [
        {},
        {}
      ]
    },
    {
      "id": "d_main_10_03_s_27",
      "group_id": "d_main_10_03_s",
      "speech_window": "Speech",
      "highlight": "emma",
      "speaker": "emma",
      "scenario_localkey": "d_main_10_03_s_27",
      "play_lipSync": true,
      "characters": [
        {
          "set_char_position": "1",
          "set_char_anim": "angry"
        },
        {},
        {
          "set_char_position": "13",
          "set_char_anim": "idle"
        },
        {},
        {},
        {},
        {},
        {},
        {},
        {}
      ],
      "set_start_camera": "130",
      "set_end_camera": "130",
      "set_camera_duration": 1.0,
      "effects": [
        {},
        {}
      ]
    }
  ]
}