{
  "version": "0.0.1",
  "records": [
    {
      "id": 9901001,
      "chapter": 2,
      "chapter_mod": "Normal",
      "group_id": 9990001,
      "name_localkey": "9901001_name",
      "description_localkey": "9901001_description",
      "monster_stage_lv": 10,
      "dynamic_object_stage_lv": 10,
      "standard_battle_power": 1000,
      "stage_stat_increase_group_id": 10000,
      "is_use_quick_battle": true,
      "spot_autocontrol": false,
      "field_monster_id": 32200501,
      "spot_id": 6001001,
      "time_limit": 90,
      "theme": "CityForest",
      "theme_time": "Day"
    },
    {
      "id": 9901002,
      "chapter": 2,
      "chapter_mod": "Normal",
      "group_id": 9990001,
      "name_localkey": "9901002_name",
      "description_localkey": "9901002_description",
      "monster_stage_lv": 10,
      "dynamic_object_stage_lv": 10,
      "standard_battle_power": 1000,
      "stage_stat_increase_group_id": 10000,
      "is_use_quick_battle": true,
      "spot_autocontrol": false,
      "field_monster_id": 22200301,
      "spot_id": 6001002,
      "time_limit": 90,
      "theme": "CityForest",
      "theme_time": "Day"
    },
    {
      "id": 9901003,
      "chapter": 2,
      "chapter_mod": "Normal",
      "group_id": 9990001,
      "name_localkey": "9901003_name",
      "description_localkey": "9901003_description",
      "monster_stage_lv": 10,
      "dynamic_object_stage_lv": 10,
      "standard_battle_power": 1000,
      "stage_stat_increase_group_id": 10000,
      "is_use_quick_battle": true,
      "spot_autocontrol": false,
      "field_monster_id": 12200101,
      "spot_id": 6001003,
      "time_limit": 90,
      "theme": "CityForest",
      "theme_time": "Day"
    },
    {
      "id": 9901004,
      "chapter": 2,
      "chapter_mod": "Normal",
      "group_id": 9990001,
      "name_localkey": "9901004_name",
      "description_localkey": "9901004_description",
      "monster_stage_lv": 10,
      "dynamic_object_stage_lv": 10,
      "standard_battle_power": 1000,
      "stage_stat_increase_group_id": 10000,
      "is_use_quick_battle": true,
      "spot_autocontrol": false,
      "field_monster_id": 32200501,
      "spot_id": 6001004,
      "time_limit": 90,
      "theme": "CityForest",
      "theme_time": "Day"
    },
    {
      "id": 9901005,
      "chapter": 2,
      "chapter_mod": "Normal",
      "group_id": 9990002,
      "name_localkey": "9901005_name",
      "description_localkey": "9901005_description",
      "monster_stage_lv": 10,
      "dynamic_object_stage_lv": 10,
      "standard_battle_power": 1000,
      "stage_stat_increase_group_id": 10000,
      "is_use_quick_battle": true,
      "spot_autocontrol": false,
      "field_monster_id": 22100201,
      "spot_id": 6001005,
      "time_limit": 90,
      "theme": "CityForest",
      "theme_time": "Night"
    },
    {
      "id": 9901006,
      "chapter": 2,
      "chapter_mod": "Normal",
      "group_id": 9990002,
      "name_localkey": "9901006_name",
      "description_localkey": "9901006_description",
      "monster_stage_lv": 10,
      "dynamic_object_stage_lv": 10,
      "standard_battle_power": 1000,
      "stage_stat_increase_group_id": 10000,
      "is_use_quick_battle": true,
      "spot_autocontrol": false,
      "field_monster_id": 32200501,
      "spot_id": 6001010,
      "time_limit": 90,
      "theme": "CityForest",
      "theme_time": "Night"
    },
    {
      "id": 9901007,
      "chapter": 2,
      "chapter_mod": "Normal",
      "group_id": 9990002,
      "name_localkey": "9901007_name",
      "description_localkey": "9901007_description",
      "monster_stage_lv": 10,
      "dynamic_object_stage_lv": 10,
      "standard_battle_power": 1000,
      "stage_stat_increase_group_id": 10000,
      "is_use_quick_battle": true,
      "spot_autocontrol": false,
      "field_monster_id": 12100201,
      "spot_id": 6001009,
      "time_limit": 90,
      "theme": "CityForest",
      "theme_time": "Night"
    },
    {
      "id": 9902001,
      "chapter": 3,
      "chapter_mod": "Normal",
      "group_id": 9990003,
      "name_localkey": "9902001_name",
      "description_localkey": "9902001_description",
      "monster_stage_lv": 30,
      "dynamic_object_stage_lv": 30,
      "standard_battle_power": 1000,
      "stage_stat_increase_group_id": 10000,
      "is_use_quick_battle": true,
      "spot_autocontrol": false,
      "field_monster_id": 32200501,
      "spot_id": 6002001,
      "time_limit": 90,
      "theme": "CityForest",
      "theme_time": "Night"
    },
    {
      "id": 9902002,
      "chapter": 3,
      "chapter_mod": "Normal",
      "group_id": 9990003,
      "name_localkey": "9902002_name",
      "description_localkey": "9902002_description",
      "monster_stage_lv": 30,
      "dynamic_object_stage_lv": 30,
      "standard_battle_power": 1000,
      "stage_stat_increase_group_id": 10000,
      "is_use_quick_battle": true,
      "spot_autocontrol": false,
      "field_monster_id": 22200301,
      "spot_id": 6002002,
      "time_limit": 90,
      "theme": "CityForest",
      "theme_time": "Night"
    },
    {
      "id": 9902003,
      "chapter": 3,
      "chapter_mod": "Normal",
      "group_id": 9990003,
      "name_localkey": "9902003_name",
      "description_localkey": "9902003_description",
      "monster_stage_lv": 30,
      "dynamic_object_stage_lv": 30,
      "standard_battle_power": 1000,
      "stage_stat_increase_group_id": 10000,
      "is_use_quick_battle": true,
      "spot_autocontrol": false,
      "field_monster_id": 12200101,
      "spot_id": 6002004,
      "time_limit": 90,
      "theme": "CityForest",
      "theme_time": "Night"
    },
    {
      "id": 9902004,
      "chapter": 3,
      "chapter_mod": "Normal",
      "group_id": 9990004,
      "name_localkey": "9902004_name",
      "description_localkey": "9902004_description",
      "monster_stage_lv": 30,
      "dynamic_object_stage_lv": 30,
      "standard_battle_power": 1000,
      "stage_stat_increase_group_id": 10000,
      "is_use_quick_battle": true,
      "spot_autocontrol": false,
      "field_monster_id": 12200101,
      "spot_id": 6002005,
      "time_limit": 90,
      "theme": "CityForest",
      "theme_time": "Night"
    },
    {
      "id": 9902005,
      "chapter": 3,
      "chapter_mod": "Normal",
      "group_id": 9990004,
      "name_localkey": "9902005_name",
      "description_localkey": "9902005_description",
      "monster_stage_lv": 30,
      "dynamic_object_stage_lv": 30,
      "standard_battle_power": 1000,
      "stage_stat_increase_group_id": 10000,
      "is_use_quick_battle": true,
      "spot_autocontrol": false,
      "field_monster_id": 12100201,
      "spot_id": 6002009,
      "time_limit": 90,
      "theme": "CityForest",
      "theme_time": "Day"
    },
    {
      "id": 9902006,
      "chapter": 3,
      "chapter_mod": "Normal",
      "group_id": 9990004,
      "name_localkey": "9902006_name",
      "description_localkey": "9902006_description",
      "monster_stage_lv": 30,
      "dynamic_object_stage_lv": 30,
      "standard_battle_power": 1000,
      "stage_stat_increase_group_id": 10000,
      "is_use_quick_battle": true,
      "spot_autocontrol": false,
      "field_monster_id": 22100201,
      "spot_id": 6002010,
      "time_limit": 90,
      "theme": "CityForest",
      "theme_time": "Day"
    }
  ]
}